esridumpgdf/__init__.py
esridumpgdf/_base.py
esridumpgdf/layer.py
esridumpgdf/service.py
esridumpgdf/site.py
esridumpgdf-0.1.1.dist-info/LICENSE
esridumpgdf-0.1.1.dist-info/WHEEL
esridumpgdf-0.1.1.dist-info/METADATA
esridumpgdf-0.1.1.dist-info/RECORD
