Metadata-Version: 2.1
Name: esridumpgdf
Version: 0.1.1
Summary: 
License: MIT
Author: wchatx
Author-email: wchatx@gmail.com
Requires-Python: >=3.8,<4.0
Classifier: License :: OSI Approved :: MIT License
Classifier: Programming Language :: Python :: 3
Classifier: Programming Language :: Python :: 3.10
Classifier: Programming Language :: Python :: 3.8
Classifier: Programming Language :: Python :: 3.9
Requires-Dist: esridump (>=1.10.1,<2.0.0)
Requires-Dist: geopandas (>=0.10.2,<0.11.0)
